AUTHORS
CHANGELOG.txt
DESCRIPTION
LICENSE
MANIFEST.in
setup.py
django_tagging_translated.egg-info/PKG-INFO
django_tagging_translated.egg-info/SOURCES.txt
django_tagging_translated.egg-info/dependency_links.txt
django_tagging_translated.egg-info/top_level.txt
tagging_translated/__init__.py
tagging_translated/admin.py
tagging_translated/models.py
tagging_translated/simple_translate.py
tagging_translated/views.py
tagging_translated/migrations/0001_initial.py
tagging_translated/migrations/0002_create_translations_for_existing_tags.py
tagging_translated/migrations/__init__.py