Metadata-Version: 1.0
Name: django-tagging-translated
Version: 0.1
Summary: Registers the Tag model for simple-translation and extends the Tag admin.
